aws_sigv4/__init__.py
aws_sigv4/create_signature.py
aws_sigv4-0.0.1.dist-info/licenses/LICENSE
aws_sigv4-0.0.1.dist-info/METADATA
aws_sigv4-0.0.1.dist-info/WHEEL
aws_sigv4-0.0.1.dist-info/top_level.txt
aws_sigv4-0.0.1.dist-info/RECORD
